{
	"format_version": "1.16.100",
	"minecraft:item": {
		"description": {
			"identifier": "guns:benelli_m3",
			"category": "equipment" // The creative inventory or recipe book tab that the block is placed into
			},
		"components": {
			"minecraft:icon": {
				"texture": "guns_benelli_m3"
			},
			"minecraft:hover_text_color": "dark_aqua",
			"minecraft:display_name": {
				"value": "Benelli M3\n12 Guage" //What the gun shows as its display text
			},
			"minecraft:cooldown": {
				"category": "m3",
				"duration": 0.25
			},
			"minecraft:durability": {
				"max_durability": 9
			},
			"minecraft:max_stack_size": 1,
			"minecraft:hand_equipped": true,
			"minecraft:on_use": {
				"on_use": {
					"event": "guns:benellim3_shoot"
				}
			},
			"minecraft:render_offsets": {
				"main_hand": {
					"first_person": {
						"position": [
							0.5,
							0.5,
							-1.5
						],
						"rotation": [
							0,
							270,
							90
						],
						"scale": [
							0.025,
							0.025,
							0.025
						]
					},
					"third_person": {
						"position": [
							-1.6,
							2.1,
							1.1
						],
						"rotation": [
							45,
							190,
							90
						],
						"scale": [
							0.03,
							0.03,
							0.03
						]
					}
				}
			}
		},
			"events": {
				"guns:benellim3_shoot": {
					"sequence": [
						{
							"condition": "q.remaining_durability>1",
							"shoot": {
								"projectile": "guns:bullet_12guage",
								"launch_power": 6
							}
						},
						{
							"condition": "q.remaining_durability>1",
							"shoot": {
								"projectile": "guns:bullet_12guage",
								"launch_power": 6
							}
						},
						{
							"condition": "q.remaining_durability>1",
							"shoot": {
								"projectile": "guns:bullet_12guage",
								"launch_power": 6
							}
						},
						{
							"condition": "q.remaining_durability>1",
							"shoot": {
								"projectile": "guns:bullet_12guage",
								"launch_power": 6
							}
						},
						{
							"condition": "q.remaining_durability>1",
							"shoot": {
								"projectile": "guns:bullet_12guage",
								"launch_power": 6
							}
						},
						{
							"condition": "q.remaining_durability>1",
							"shoot": {
								"projectile": "guns:bullet_12guage",
								"launch_power": 6
							}
						},
						{
							"condition": "q.remaining_durability>1",
							"shoot": {
								"projectile": "guns:bullet_12guage",
								"launch_power": 6
							}
						},
						{
							"condition": "q.remaining_durability>1",
							"shoot": {
								"projectile": "guns:bullet_12guage",
								"launch_power": 6
							}
						},
						{
							"condition": "q.remaining_durability>1",
							"shoot": {
								"projectile": "guns:bullet_12guage",
								"launch_power": 6
							}
						},
						{
							"condition": "q.remaining_durability>1",
							"shoot": {
								"projectile": "guns:bullet_12guage",
								"launch_power": 6
							}
						},
						{
							"condition": "q.remaining_durability>1",
							"shoot": {
								"projectile": "guns:bullet_12guage",
								"launch_power": 6
							}
						},
						{
							"condition": "q.remaining_durability>1",
							"shoot": {
								"projectile": "guns:bullet_12guage",
								"launch_power": 6
							}
						},
						{
							"condition": "q.remaining_durability>1",
							"shoot": {
								"projectile": "guns:bullet_12guage",
								"launch_power": 6
							}
						},
						{
							"condition": "q.remaining_durability>1",
							"shoot": {
								"projectile": "guns:bullet_12guage",
								"launch_power": 6
							}
						},
						{
							"condition": "q.remaining_durability>1",
							"shoot": {
								"projectile": "guns:bullet_12guage",
								"launch_power": 6
							}
						},
						{
							"condition": "q.remaining_durability>1",
							"shoot": {
								"projectile": "guns:bullet_12guage",
								"launch_power": 6
							}
						},
						{
							"condition": "q.remaining_durability>1",
							"shoot": {
								"projectile": "guns:bullet_12guage",
								"launch_power": 6
							}
						},
						{
							"condition": "q.remaining_durability>1",
							"shoot": {
								"projectile": "guns:bullet_12guage",
								"launch_power": 6
							}
						},
						{
							"condition": "q.remaining_durability>1",
							"shoot": {
								"projectile": "guns:bullet_12guage",
								"launch_power": 6
							}
						},
						{
							"condition": "q.remaining_durability>1",
							"shoot": {
								"projectile": "guns:bullet_12guage",
								"launch_power": 6
							}
						},
						{
							"condition": "q.remaining_durability>1",
							"damage": {
								"type": "durability",
								"amount": 1,
								"target": "self"
							}
						},
						{
							"condition": "q.remaining_durability>1",
							"run_command": {
								"command": [
									"playsound guns.benellim3.fire @a ~ ~ ~ 1 1 0"
								]
							}
						},

						{
							"condition": "q.remaining_durability>1 && query.is_sneaking",
							"run_command": {
								"command": [
									"camerashake add @s 0.003 1 rotational"
								]
							}
						},
						{
							"condition": "q.remaining_durability>1 && !query.is_sneaking",
							"run_command": {
								"command": [
									"camerashake add @s 0.01 1 rotational"
								]
							}
						},
						{
							"condition": "q.remaining_durability>1 && query.is_sprinting",
							"run_command": {
								"command": [
									"camerashake add @s 0.04 1 rotational"
								]
							}
						},
						{
							"condition": "q.remaining_durability==1",
							"run_command": {
								"command": [
									"title @s actionbar Ammo 0/8",
									"replaceitem entity @s slot.weapon.mainhand 0 guns:benellim3_empty"
								]
							}
						},
						{
							"condition": "q.remaining_durability==2",
							"run_command": {
								"command": [
									"title @s actionbar Ammo 1/8"
								]
							}
						},
						{
							"condition": "q.remaining_durability==3",
							"run_command": {
								"command": [
									"title @s actionbar Ammo 2/8"
								]
							}
						},
						{
							"condition": "q.remaining_durability==4",
							"run_command": {
								"command": [
									"title @s actionbar Ammo 3/8"
								]
							}
						},
						{
							"condition": "q.remaining_durability==5",
							"run_command": {
								"command": [
									"title @s actionbar Ammo 4/8"
								]
							}
						},
						{
							"condition": "q.remaining_durability==6",
							"run_command": {
								"command": [
									"title @s actionbar Ammo 5/8"
								]
							}
						},
						{
							"condition": "q.remaining_durability==7",
							"run_command": {
								"command": [
									"title @s actionbar Ammo 6/8"
								]
							}
						},
						{
							"condition": "q.remaining_durability==8",
							"run_command": {
								"command": [
									"title @s actionbar Ammo 7/8"
								]
							}
						}
					]
				}
			}
		}
}